{
  "AAPL": {
    "buy_threshold": -0.05,
    "last_optimized": "2026-04-03T17:17:10.710Z",
    "price_flag": 3,
    "sell_threshold": -0.05,
    "test_metrics": {
      "avg_yr_return": 0.347228,
      "recovery_period": 1.28
    },
    "train_metrics": {
      "avg_yr_return": 0.18244,
      "recovery_period": 4.84
    },
    "vol_flag": 1,
    "vol_price_mix": 0.8
  },
  "AAUC": {
    "buy_threshold": -0.038,
    "last_optimized": "2026-04-03T17:26:40.638Z",
    "price_flag": 0,
    "sell_threshold": -0.038,
    "test_metrics": {
      "avg_yr_return": 3.833646,
      "recovery_period": 0.22
    },
    "train_metrics": {
      "avg_yr_return": 2.809703,
      "recovery_period": 0.36
    },
    "vol_flag": 2,
    "vol_price_mix": 0
  },
  "AMD": {
    "buy_threshold": -0.02,
    "last_optimized": "2026-04-03T17:17:10.710Z",
    "price_flag": 0,
    "sell_threshold": -0.02,
    "test_metrics": {
      "avg_yr_return": -0.039235,
      "recovery_period": 999
    },
    "train_metrics": {
      "avg_yr_return": 0.319694,
      "recovery_period": 4.69
    },
    "vol_flag": 3,
    "vol_price_mix": 0.8
  },
  "ANET": {
    "buy_threshold": 0,
    "last_optimized": "2026-04-02T22:10:14.519Z",
    "price_flag": 2,
    "sell_threshold": 0,
    "test_metrics": {
      "avg_yr_return": -0.197865,
      "recovery_period": 999
    },
    "train_metrics": {
      "avg_yr_return": 0.56202,
      "recovery_period": 1.51
    },
    "vol_flag": 3,
    "vol_price_mix": 0
  },
  "AVGO": {
    "buy_threshold": -0.003,
    "last_optimized": "2026-04-02T22:10:05.962Z",
    "price_flag": 2,
    "sell_threshold": -0.003,
    "test_metrics": {
      "avg_yr_return": -0.065084,
      "recovery_period": 999
    },
    "train_metrics": {
      "avg_yr_return": 0.514132,
      "recovery_period": 1.91
    },
    "vol_flag": 2,
    "vol_price_mix": 0.02
  },
  "COST": {
    "buy_threshold": -0.027,
    "last_optimized": "2026-04-02T22:10:30.928Z",
    "price_flag": 0,
    "sell_threshold": -0.027,
    "test_metrics": {
      "avg_yr_return": -0.02821,
      "recovery_period": 999
    },
    "train_metrics": {
      "avg_yr_return": 0.343738,
      "recovery_period": 1.83
    },
    "vol_flag": 1,
    "vol_price_mix": 0
  },
  "GLDM": {
    "buy_threshold": -0.007,
    "last_optimized": "2026-04-02T22:09:56.789Z",
    "price_flag": 0,
    "sell_threshold": -0.007,
    "test_metrics": {
      "avg_yr_return": 0.771741,
      "recovery_period": 0.37
    },
    "train_metrics": {
      "avg_yr_return": 0.20192,
      "recovery_period": 1.82
    },
    "vol_flag": 3,
    "vol_price_mix": 0.16
  },
  "GOOG": {
    "buy_threshold": 0.0055,
    "last_optimized": "2026-04-02T22:10:52.196Z",
    "price_flag": 1,
    "sell_threshold": 0.0055,
    "test_metrics": {
      "avg_yr_return": 0.875674,
      "recovery_period": 0.46
    },
    "train_metrics": {
      "avg_yr_return": 0.132218,
      "recovery_period": 4.06
    },
    "vol_flag": 2,
    "vol_price_mix": 0.18
  },
  "IWF": {
    "buy_threshold": -0.02,
    "last_optimized": "2026-04-03T17:17:10.710Z",
    "price_flag": 2,
    "sell_threshold": -0.02,
    "test_metrics": {
      "avg_yr_return": 0.166063,
      "recovery_period": 1.11
    },
    "train_metrics": {
      "avg_yr_return": 0.161329,
      "recovery_period": 3.56
    },
    "vol_flag": 2,
    "vol_price_mix": 0.4
  },
  "LLY": {
    "buy_threshold": -0.03,
    "last_optimized": "2026-04-03T17:17:10.710Z",
    "price_flag": 0,
    "sell_threshold": -0.03,
    "test_metrics": {
      "avg_yr_return": 0.012595,
      "recovery_period": 58.14
    },
    "train_metrics": {
      "avg_yr_return": 0.43374,
      "recovery_period": 1.71
    },
    "vol_flag": 0,
    "vol_price_mix": 0
  },
  "MSFT": {
    "buy_threshold": 0.006,
    "last_optimized": "2026-04-02T22:14:30.825Z",
    "price_flag": 2,
    "sell_threshold": 0.006,
    "test_metrics": {
      "avg_yr_return": -0.097764,
      "recovery_period": 999
    },
    "train_metrics": {
      "avg_yr_return": 0.138158,
      "recovery_period": 2.8
    },
    "vol_flag": 1,
    "vol_price_mix": 0.1
  },
  "MU": {
    "buy_threshold": 0.0775,
    "last_optimized": "2026-04-02T22:14:22.084Z",
    "price_flag": 2,
    "sell_threshold": 0.0775,
    "test_metrics": {
      "avg_yr_return": 1.313437,
      "recovery_period": 0.55
    },
    "train_metrics": {
      "avg_yr_return": 0.12668,
      "recovery_period": 3.85
    },
    "vol_flag": 1,
    "vol_price_mix": 0.4
  },
  "NRG": {
    "buy_threshold": 0,
    "last_optimized": "2026-04-03T17:17:10.710Z",
    "price_flag": 0,
    "sell_threshold": 0,
    "test_metrics": {
      "avg_yr_return": -0.042004,
      "recovery_period": 999
    },
    "train_metrics": {
      "avg_yr_return": 0.393646,
      "recovery_period": 2.42
    },
    "vol_flag": 3,
    "vol_price_mix": 1
  },
  "NVDA": {
    "buy_threshold": -0.04,
    "last_optimized": "2026-04-03T17:17:10.710Z",
    "price_flag": 0,
    "sell_threshold": -0.04,
    "test_metrics": {
      "avg_yr_return": 0.026071,
      "recovery_period": 15.9
    },
    "train_metrics": {
      "avg_yr_return": 0.69917,
      "recovery_period": 2.68
    },
    "vol_flag": 2,
    "vol_price_mix": 0.8
  },
  "PANW": {
    "buy_threshold": -0.1,
    "last_optimized": "2026-04-03T17:17:10.710Z",
    "price_flag": 2,
    "sell_threshold": -0.1,
    "test_metrics": {
      "avg_yr_return": -0.045858,
      "recovery_period": 999
    },
    "train_metrics": {
      "avg_yr_return": 0.28374,
      "recovery_period": 2.51
    },
    "vol_flag": 0,
    "vol_price_mix": 0.2
  },
  "PLTR": {
    "buy_threshold": -0.1,
    "last_optimized": "2026-04-03T17:17:10.710Z",
    "price_flag": 2,
    "sell_threshold": -0.1,
    "test_metrics": {
      "avg_yr_return": -0.212774,
      "recovery_period": 999
    },
    "train_metrics": {
      "avg_yr_return": 0.697104,
      "recovery_period": 3.59
    },
    "vol_flag": 2,
    "vol_price_mix": 0.8
  },
  "PM": {
    "buy_threshold": -0.0005,
    "last_optimized": "2026-04-02T22:13:54.804Z",
    "price_flag": 0,
    "sell_threshold": -0.0005,
    "test_metrics": {
      "avg_yr_return": -0.140825,
      "recovery_period": 999
    },
    "train_metrics": {
      "avg_yr_return": 0.260793,
      "recovery_period": 1.26
    },
    "vol_flag": 2,
    "vol_price_mix": 0.04
  },
  "QQQ": {
    "buy_threshold": -0.0035,
    "last_optimized": "2026-04-02T22:10:27.318Z",
    "price_flag": 2,
    "sell_threshold": -0.0035,
    "test_metrics": {
      "avg_yr_return": 0.036195,
      "recovery_period": 4.74
    },
    "train_metrics": {
      "avg_yr_return": 0.154728,
      "recovery_period": 2.03
    },
    "vol_flag": 2,
    "vol_price_mix": 0.42
  },
  "RCL": {
    "buy_threshold": -0.01,
    "last_optimized": "2026-04-03T17:17:10.710Z",
    "price_flag": 3,
    "sell_threshold": -0.01,
    "test_metrics": {
      "avg_yr_return": -0.396463,
      "recovery_period": 999
    },
    "train_metrics": {
      "avg_yr_return": 0.51723,
      "recovery_period": 2.07
    },
    "vol_flag": 3,
    "vol_price_mix": 0.2
  },
  "SHOP": {
    "buy_threshold": -0.06,
    "last_optimized": "2026-04-03T17:17:10.710Z",
    "price_flag": 0,
    "sell_threshold": -0.06,
    "test_metrics": {
      "avg_yr_return": 0.039604,
      "recovery_period": 22.96
    },
    "train_metrics": {
      "avg_yr_return": 0.302643,
      "recovery_period": 3.93
    },
    "vol_flag": 3,
    "vol_price_mix": 1
  },
  "SIVR": {
    "buy_threshold": -0.0175,
    "last_optimized": "2026-04-02T22:10:39.201Z",
    "price_flag": 0,
    "sell_threshold": -0.0175,
    "test_metrics": {
      "avg_yr_return": 2.128765,
      "recovery_period": 0.84
    },
    "train_metrics": {
      "avg_yr_return": 0.294191,
      "recovery_period": 1.43
    },
    "vol_flag": 2,
    "vol_price_mix": 0.16
  },
  "SPY": {
    "buy_threshold": 0,
    "last_optimized": "2026-04-03T17:17:10.710Z",
    "price_flag": 1,
    "sell_threshold": 0,
    "test_metrics": {
      "avg_yr_return": 0.213778,
      "recovery_period": 0.96
    },
    "train_metrics": {
      "avg_yr_return": 0.104904,
      "recovery_period": 3.87
    },
    "vol_flag": 0,
    "vol_price_mix": 0
  },
  "TPR": {
    "buy_threshold": -0.06,
    "last_optimized": "2026-04-03T17:17:10.710Z",
    "price_flag": 3,
    "sell_threshold": -0.06,
    "test_metrics": {
      "avg_yr_return": 0.780531,
      "recovery_period": 0.59
    },
    "train_metrics": {
      "avg_yr_return": 0.455559,
      "recovery_period": 2.89
    },
    "vol_flag": 2,
    "vol_price_mix": 0.6
  },
  "TSLA": {
    "buy_threshold": -0.102,
    "last_optimized": "2026-04-02T22:14:26.234Z",
    "price_flag": 0,
    "sell_threshold": -0.102,
    "test_metrics": {
      "avg_yr_return": 0.025184,
      "recovery_period": 33.99
    },
    "train_metrics": {
      "avg_yr_return": 0.462781,
      "recovery_period": 3.01
    },
    "vol_flag": 0,
    "vol_price_mix": 0.12
  },
  "TSM": {
    "buy_threshold": -0.0045,
    "last_optimized": "2026-04-02T22:14:13.101Z",
    "price_flag": 3,
    "sell_threshold": -0.0045,
    "test_metrics": {
      "avg_yr_return": 0.203176,
      "recovery_period": 2.16
    },
    "train_metrics": {
      "avg_yr_return": 0.206298,
      "recovery_period": 3.82
    },
    "vol_flag": 1,
    "vol_price_mix": 0.16
  },
  "USO": {
    "buy_threshold": -0.09,
    "last_optimized": "2026-04-03T17:17:10.710Z",
    "price_flag": 0,
    "sell_threshold": -0.09,
    "test_metrics": {
      "avg_yr_return": 1.793136,
      "recovery_period": 0.3
    },
    "train_metrics": {
      "avg_yr_return": 0.300303,
      "recovery_period": 3.16
    },
    "vol_flag": 2,
    "vol_price_mix": 0.2
  },
  "XLE": {
    "buy_threshold": -0.09,
    "last_optimized": "2026-04-02T22:10:47.546Z",
    "price_flag": 0,
    "sell_threshold": -0.09,
    "test_metrics": {
      "avg_yr_return": 0.314585,
      "recovery_period": 0.62
    },
    "train_metrics": {
      "avg_yr_return": 0.371597,
      "recovery_period": 1.34
    },
    "vol_flag": 0,
    "vol_price_mix": 0.1
  }
}
